aporia_ast/__init__.py
aporia_ast/main.py
aporia_ast-0.1.3.dist-info/METADATA
aporia_ast-0.1.3.dist-info/WHEEL
aporia_ast-0.1.3.dist-info/top_level.txt
aporia_ast-0.1.3.dist-info/RECORD
