Metadata-Version: 2.2
Name: aporia-ast
Version: 0.1.3
Summary: Provides abstract syntax tree objects for the Aporia language
Author-email: Ephraim Siegfried <ephraim.siegfried@hotmail.com>
Requires-Python: >=3.10
